tackerclient/__init__.py
tackerclient/client.py
tackerclient/i18n.py
tackerclient/shell.py
tackerclient/version.py
tackerclient/common/__init__.py
tackerclient/common/_i18n.py
tackerclient/common/clientmanager.py
tackerclient/common/command.py
tackerclient/common/constants.py
tackerclient/common/exceptions.py
tackerclient/common/extension.py
tackerclient/common/serializer.py
tackerclient/common/utils.py
tackerclient/common/validators.py
tackerclient/osc/__init__.py
tackerclient/osc/plugin.py
tackerclient/osc/sdk_utils.py
tackerclient/osc/utils.py
tackerclient/osc/common/__init__.py
tackerclient/osc/common/vnflcm/__init__.py
tackerclient/osc/common/vnflcm/vnflcm_versions.py
tackerclient/osc/v1/__init__.py
tackerclient/osc/v1/nfvo/__init__.py
tackerclient/osc/v1/nfvo/vim.py
tackerclient/osc/v1/vnflcm/__init__.py
tackerclient/osc/v1/vnflcm/vnflcm.py
tackerclient/osc/v1/vnflcm/vnflcm_op_occs.py
tackerclient/osc/v1/vnflcm/vnflcm_subsc.py
tackerclient/osc/v1/vnflcm/samples/change_ext_conn_vnf_instance_param_sample.json
tackerclient/osc/v1/vnflcm/samples/create_lccn_subscription_param_sample.json
tackerclient/osc/v1/vnflcm/samples/heal_vnf_instance_param_sample.json
tackerclient/osc/v1/vnflcm/samples/instantiate_vnf_instance_param_sample.json
tackerclient/osc/v1/vnflcm/samples/scale_vnf_instance_param_sample.json
tackerclient/osc/v1/vnflcm/samples/update_vnf_instance_param_sample.json
tackerclient/osc/v1/vnfpkgm/__init__.py
tackerclient/osc/v1/vnfpkgm/vnf_package.py
tackerclient/osc/v2/__init__.py
tackerclient/osc/v2/vnffm/__init__.py
tackerclient/osc/v2/vnffm/vnffm_alarm.py
tackerclient/osc/v2/vnffm/vnffm_sub.py
tackerclient/osc/v2/vnffm/samples/create_vnf_fm_subscription_param_sample.json
tackerclient/osc/v2/vnflcm/samples/change_vnfpkg_vnf_instance_param_sample.json
tackerclient/osc/v2/vnfpm/__init__.py
tackerclient/osc/v2/vnfpm/vnfpm_job.py
tackerclient/osc/v2/vnfpm/vnfpm_report.py
tackerclient/osc/v2/vnfpm/vnfpm_threshold.py
python_tackerclient-2.4.0.dist-info/AUTHORS
python_tackerclient-2.4.0.dist-info/LICENSE
python_tackerclient-2.4.0.dist-info/METADATA
python_tackerclient-2.4.0.dist-info/WHEEL
python_tackerclient-2.4.0.dist-info/entry_points.txt
python_tackerclient-2.4.0.dist-info/pbr.json
python_tackerclient-2.4.0.dist-info/top_level.txt
python_tackerclient-2.4.0.dist-info/RECORD
