Metadata-Version: 2.1
Name: python-tackerclient
Version: 2.4.0
Summary: CLI and Client Library for OpenStack Tacker
Home-page: https://docs.openstack.org/python-tackerclient/
Author: OpenStack
Author-email: openstack-discuss@lists.openstack.org
Classifier: Environment :: OpenStack
Classifier: Intended Audience :: Developers
Classifier: Intended Audience :: Information Technology
Classifier: Intended Audience :: System Administrators
Classifier: License :: OSI Approved :: Apache Software License
Classifier: Operating System :: POSIX :: Linux
Classifier: Programming Language :: Python
Classifier: Programming Language :: Python :: Implementation :: CPython
Classifier: Programming Language :: Python :: 3 :: Only
Classifier: Programming Language :: Python :: 3
Classifier: Programming Language :: Python :: 3.6
Classifier: Programming Language :: Python :: 3.7
Classifier: Programming Language :: Python :: 3.8
Classifier: Programming Language :: Python :: 3.9
Classifier: Programming Language :: Python :: 3.10
Requires-Python: >=3.6
License-File: LICENSE
License-File: AUTHORS
Requires-Dist: pbr !=2.1.0,>=2.0.0
Requires-Dist: cliff !=2.9.0,>=2.8.0
Requires-Dist: iso8601 >=0.1.11
Requires-Dist: netaddr >=0.7.18
Requires-Dist: requests >=2.14.2
Requires-Dist: python-keystoneclient >=3.8.0
Requires-Dist: stevedore >=1.20.0
Requires-Dist: Babel !=2.4.0,>=2.3.4
Requires-Dist: oslo.i18n >=3.15.3
Requires-Dist: osc-lib >=1.8.0
Requires-Dist: oslo.utils >=3.40.0
Requires-Dist: oslo.serialization !=2.19.1,>=2.18.0
